huggingface_hub/__init__.py
huggingface_hub/_commit_api.py
huggingface_hub/_commit_scheduler.py
huggingface_hub/_inference_endpoints.py
huggingface_hub/_jobs_api.py
huggingface_hub/_local_folder.py
huggingface_hub/_login.py
huggingface_hub/_oauth.py
huggingface_hub/_snapshot_download.py
huggingface_hub/_space_api.py
huggingface_hub/_tensorboard_logger.py
huggingface_hub/_upload_large_folder.py
huggingface_hub/_webhooks_payload.py
huggingface_hub/_webhooks_server.py
huggingface_hub/community.py
huggingface_hub/constants.py
huggingface_hub/dataclasses.py
huggingface_hub/errors.py
huggingface_hub/fastai_utils.py
huggingface_hub/file_download.py
huggingface_hub/hf_api.py
huggingface_hub/hf_file_system.py
huggingface_hub/hub_mixin.py
huggingface_hub/lfs.py
huggingface_hub/py.typed
huggingface_hub/repocard.py
huggingface_hub/repocard_data.py
huggingface_hub/cli/__init__.py
huggingface_hub/cli/_cli_utils.py
huggingface_hub/cli/auth.py
huggingface_hub/cli/cache.py
huggingface_hub/cli/download.py
huggingface_hub/cli/hf.py
huggingface_hub/cli/inference_endpoints.py
huggingface_hub/cli/jobs.py
huggingface_hub/cli/lfs.py
huggingface_hub/cli/repo.py
huggingface_hub/cli/repo_files.py
huggingface_hub/cli/system.py
huggingface_hub/cli/upload.py
huggingface_hub/cli/upload_large_folder.py
huggingface_hub/inference/__init__.py
huggingface_hub/inference/_client.py
huggingface_hub/inference/_common.py
huggingface_hub/inference/_generated/__init__.py
huggingface_hub/inference/_generated/_async_client.py
huggingface_hub/inference/_generated/types/__init__.py
huggingface_hub/inference/_generated/types/audio_classification.py
huggingface_hub/inference/_generated/types/audio_to_audio.py
huggingface_hub/inference/_generated/types/automatic_speech_recognition.py
huggingface_hub/inference/_generated/types/base.py
huggingface_hub/inference/_generated/types/chat_completion.py
huggingface_hub/inference/_generated/types/depth_estimation.py
huggingface_hub-1.1.0.dist-info/licenses/LICENSE
huggingface_hub-1.1.0.dist-info/METADATA
huggingface_hub-1.1.0.dist-info/WHEEL
huggingface_hub-1.1.0.dist-info/entry_points.txt
huggingface_hub-1.1.0.dist-info/top_level.txt
huggingface_hub-1.1.0.dist-info/RECORD
