Metadata-Version: 2.4
Name: huggingface_hub
Version: 1.1.0
Summary: Client library to download and publish models, datasets and other repos on the huggingface.co hub
Home-page: https://github.com/huggingface/huggingface_hub
Author: Hugging Face, Inc.
Author-email: julien@huggingface.co
License: Apache
Keywords: model-hub machine-learning models natural-language-processing deep-learning pytorch pretrained-models
Classifier: Intended Audience :: Developers
Classifier: Intended Audience :: Education
Classifier: Intended Audience :: Science/Research
Classifier: License :: OSI Approved :: Apache Software License
Classifier: Operating System :: OS Independent
Classifier: Programming Language :: Python :: 3
Classifier: Programming Language :: Python :: 3 :: Only
Classifier: Programming Language :: Python :: 3.9
Classifier: Programming Language :: Python :: 3.10
Classifier: Programming Language :: Python :: 3.11
Classifier: Programming Language :: Python :: 3.12
Classifier: Programming Language :: Python :: 3.13
Classifier: Programming Language :: Python :: 3.14
Classifier: Topic :: Scientific/Engineering :: Artificial Intelligence
Requires-Python: >=3.9.0
License-File: LICENSE
Requires-Dist: filelock
Requires-Dist: fsspec>=2023.5.0
Requires-Dist: hf-xet<2.0.0,>=1.2.0; platform_machine == "x86_64" or platform_machine == "amd64" or platform_machine == "AMD64" or platform_machine == "arm64" or platform_machine == "aarch64"
Requires-Dist: httpx<1,>=0.23.0
Requires-Dist: packaging>=20.9
Requires-Dist: pyyaml>=5.1
Requires-Dist: shellingham
Requires-Dist: tqdm>=4.42.1
Requires-Dist: typer-slim
Requires-Dist: typing-extensions>=3.7.4.3
Provides-Extra: oauth
Requires-Dist: authlib>=1.3.2; extra == "oauth"
Requires-Dist: fastapi; extra == "oauth"
Requires-Dist: httpx; extra == "oauth"
Requires-Dist: itsdangerous; extra == "oauth"
Provides-Extra: torch
Requires-Dist: torch; extra == "torch"
Requires-Dist: safetensors[torch]; extra == "torch"
Provides-Extra: fastai
Requires-Dist: toml; extra == "fastai"
Requires-Dist: fastai>=2.4; extra == "fastai"
Requires-Dist: fastcore>=1.3.27; extra == "fastai"
Provides-Extra: hf-xet
Requires-Dist: hf-xet<2.0.0,>=1.1.3; extra == "hf-xet"
Provides-Extra: mcp
Requires-Dist: mcp>=1.8.0; extra == "mcp"
Provides-Extra: testing
Requires-Dist: authlib>=1.3.2; extra == "testing"
Requires-Dist: fastapi; extra == "testing"
Requires-Dist: httpx; extra == "testing"
Requires-Dist: itsdangerous; extra == "testing"
Requires-Dist: jedi; extra == "testing"
Requires-Dist: Jinja2; extra == "testing"
Requires-Dist: pytest>=8.4.2; extra == "testing"
Requires-Dist: pytest-cov; extra == "testing"
Requires-Dist: pytest-env; extra == "testing"
Requires-Dist: pytest-xdist; extra == "testing"
Requires-Dist: pytest-vcr; extra == "testing"
Requires-Dist: pytest-asyncio; extra == "testing"
Requires-Dist: pytest-rerunfailures<16.0; extra == "testing"
Requires-Dist: pytest-mock; extra == "testing"
Requires-Dist: urllib3<2.0; extra == "testing"
Requires-Dist: soundfile; extra == "testing"
Requires-Dist: Pillow; extra == "testing"
Requires-Dist: numpy; extra == "testing"
Requires-Dist: fastapi; extra == "testing"
Provides-Extra: typing
Requires-Dist: typing-extensions>=4.8.0; extra == "typing"
Requires-Dist: types-PyYAML; extra == "typing"
Requires-Dist: types-simplejson; extra == "typing"
Requires-Dist: types-toml; extra == "typing"
Requires-Dist: types-tqdm; extra == "typing"
Requires-Dist: types-urllib3; extra == "typing"
Provides-Extra: quality
Requires-Dist: ruff>=0.9.0; extra == "quality"
Requires-Dist: mypy==1.15.0; extra == "quality"
Requires-Dist: libcst>=1.4.0; extra == "quality"
Requires-Dist: ty; extra == "quality"
Provides-Extra: all
Requires-Dist: authlib>=1.3.2; extra == "all"
Requires-Dist: fastapi; extra == "all"
Requires-Dist: httpx; extra == "all"
Requires-Dist: itsdangerous; extra == "all"
Requires-Dist: jedi; extra == "all"
Requires-Dist: Jinja2; extra == "all"
Requires-Dist: pytest>=8.4.2; extra == "all"
Requires-Dist: pytest-cov; extra == "all"
Requires-Dist: pytest-env; extra == "all"
Requires-Dist: pytest-xdist; extra == "all"
Requires-Dist: pytest-vcr; extra == "all"
Requires-Dist: pytest-asyncio; extra == "all"
Requires-Dist: pytest-rerunfailures<16.0; extra == "all"
Requires-Dist: pytest-mock; extra == "all"
Requires-Dist: urllib3<2.0; extra == "all"
Requires-Dist: soundfile; extra == "all"
Requires-Dist: Pillow; extra == "all"
Requires-Dist: numpy; extra == "all"
Requires-Dist: fastapi; extra == "all"
Requires-Dist: ruff>=0.9.0; extra == "all"
Requires-Dist: mypy==1.15.0; extra == "all"
Requires-Dist: libcst>=1.4.0; extra == "all"
Requires-Dist: ty; extra == "all"
Requires-Dist: typing-extensions>=4.8.0; extra == "all"
Requires-Dist: types-PyYAML; extra == "all"
Requires-Dist: types-simplejson; extra == "all"
Requires-Dist: types-toml; extra == "all"
Requires-Dist: types-tqdm; extra == "all"
Requires-Dist: types-urllib3; extra == "all"
Provides-Extra: dev
Requires-Dist: authlib>=1.3.2; extra == "dev"
Requires-Dist: fastapi; extra == "dev"
Requires-Dist: httpx; extra == "dev"
Requires-Dist: itsdangerous; extra == "dev"
Requires-Dist: jedi; extra == "dev"
Requires-Dist: Jinja2; extra == "dev"
Requires-Dist: pytest>=8.4.2; extra == "dev"
Requires-Dist: pytest-cov; extra == "dev"
Requires-Dist: pytest-env; extra == "dev"
Requires-Dist: pytest-xdist; extra == "dev"
Requires-Dist: pytest-vcr; extra == "dev"
Requires-Dist: pytest-asyncio; extra == "dev"
Requires-Dist: pytest-rerunfailures<16.0; extra == "dev"
Requires-Dist: pytest-mock; extra == "dev"
Requires-Dist: urllib3<2.0; extra == "dev"
Requires-Dist: soundfile; extra == "dev"
Requires-Dist: Pillow; extra == "dev"
Requires-Dist: numpy; extra == "dev"
Requires-Dist: fastapi; extra == "dev"
Requires-Dist: ruff>=0.9.0; extra == "dev"
Requires-Dist: mypy==1.15.0; extra == "dev"
Requires-Dist: libcst>=1.4.0; extra == "dev"
Requires-Dist: ty; extra == "dev"
Requires-Dist: typing-extensions>=4.8.0; extra == "dev"
Requires-Dist: types-PyYAML; extra == "dev"
Requires-Dist: types-simplejson; extra == "dev"
Requires-Dist: types-toml; extra == "dev"
Requires-Dist: types-tqdm; extra == "dev"
Requires-Dist: types-urllib3; extra == "dev"
Dynamic: author
Dynamic: author-email
Dynamic: classifier
Dynamic: description
Dynamic: description-content-type
Dynamic: home-page
Dynamic: keywords
Dynamic: license
Dynamic: license-file
Dynamic: provides-extra
Dynamic: requires-dist
Dynamic: requires-python
Dynamic: summary
